Metadata-Version: 1.0
Name: devilparser
Version: 0.0.7
Summary: Load RC type files with the ability to use shell commands like lpass to get passwords
Home-page: UNKNOWN
Author: Drew Stinnett
Author-email: drew@drewlink.com
License: BSD
Keywords: lpass secuirty config
Platform: UNKNOWN
